{
  "sablons": [
    {
      "ID": "5d16be9a-703e-45eb-9f24-dac4e3b0c1f2",
      "Source_Api": "ProdMgmt/Parts('OR:wt.part.WTPart:",
      "State": "RELEASED",
      "Api_adres": "http://localhost:7217/api",
      "Ana_kaynak": "PART",
      "Alt_endpoint": "RELEASED_PART",
      "sablonDataDurumu": "true",
      "sablonName": "PARTS - RELEASED",
      "sablonData": [
        {
          "ID": "98f08256-7d3a-489d-8f47-37561267c838",
          "Name": "source_Api",
          "SQLName": "source_Api",
          "IsActive": "ProdMgmt/Parts('OR:wt.part.WTPart:"
        },
        {
          "ID": "f943d91b-6c30-49ab-821f-564dda9383e3",
          "Name": "yapilacakIslem",
          "SQLName": "yapilacakIslem",
          "IsActive": "RELEASED"
        },
        {
          "ID": "d1df42f9-bed5-4f6a-9a32-d03ff9f79aaf",
          "Name": "api_adres",
          "SQLName": "api_adres",
          "IsActive": "http://localhost:7217/api"
        },
        {
          "ID": "2c2a8ee9-78d9-4a66-b066-15009727e7a2",
          "Name": "ana_kaynak",
          "SQLName": "ana_kaynak",
          "IsActive": "PART"
        },
        {
          "ID": "256c5f41-cccc-4c34-805e-097685bc7b1b",
          "Name": "alt_endpoint",
          "SQLName": "alt_endpoint",
          "IsActive": "RELEASED_PART"
        },
        {
          "ID": "d2cbd1f1-2461-4c20-8cde-f1584649db19",
          "Name": "CreatedOn",
          "SQLName": "CreatedOn",
          "IsActive": "true"
        },
        {
          "ID": "0cf1b90a-af9e-4ce7-83a3-31af5f0bd121",
          "Name": "ID",
          "SQLName": "ID",
          "IsActive": "true"
        },
        {
          "ID": "74f97455-ad00-4a17-ab5d-61542f790061",
          "Name": "LastModified",
          "SQLName": "LastModified",
          "IsActive": "true"
        },
        {
          "ID": "9038b6ce-8110-43de-8c37-7044ffcc9ce6",
          "Name": "AlternateNumber",
          "SQLName": "AlternateNumber",
          "IsActive": "true"
        },
        {
          "ID": "299f2318-c85c-4696-8a1c-68ac9d33beea",
          "Name": "AssemblyModeValue",
          "SQLName": "AssemblyModeValue",
          "IsActive": "true"
        },
        {
          "ID": "6813b3c6-e011-4e3e-8e8b-8b026be88729",
          "Name": "BOMType",
          "SQLName": "BOMType",
          "IsActive": "true"
        },
        {
          "ID": "7f790a75-d086-4109-9d57-92fd9ae806bc",
          "Name": "CADName",
          "SQLName": "CADName",
          "IsActive": "true"
        },
        {
          "ID": "cbf8c67f-39be-4b60-9ee0-7e11ae7ed03a",
          "Name": "CLASSIFICATION",
          "SQLName": "CLASSIFICATION",
          "IsActive": "true"
        },
        {
          "ID": "0e3f1e72-218e-4e2f-ad68-bb144b4cf128",
          "Name": "CabinetName",
          "SQLName": "CabinetName",
          "IsActive": "true"
        },
        {
          "ID": "534103af-525a-4d56-b784-af81d415d0cf",
          "Name": "ChangeStatus",
          "SQLName": "ChangeStatus",
          "IsActive": "true"
        },
        {
          "ID": "05a21c5f-fa68-4298-99d8-6c426862cd4e",
          "Name": "CheckOutStatus",
          "SQLName": "CheckOutStatus",
          "IsActive": "true"
        },
        {
          "ID": "a4d7c75d-3e21-4942-9182-ab8bf7afa2fb",
          "Name": "CheckoutState",
          "SQLName": "CheckoutState",
          "IsActive": "true"
        },
        {
          "ID": "187fc7a5-e3c9-4608-b6c8-8c8756f2bcba",
          "Name": "Comments",
          "SQLName": "Comments",
          "IsActive": "true"
        },
        {
          "ID": "954a9976-03f3-4aed-8dea-a928746e7c1d",
          "Name": "ComponentType",
          "SQLName": "ComponentType",
          "IsActive": "true"
        },
        {
          "ID": "1e1984d5-c5cc-4875-b48c-a0092a206618",
          "Name": "ConfigurableModuleValue",
          "SQLName": "ConfigurableModuleValue",
          "IsActive": "true"
        },
        {
          "ID": "f1abbee8-3734-49aa-b67d-42093b9029fb",
          "Name": "CreatedBy",
          "SQLName": "CreatedBy",
          "IsActive": "true"
        },
        {
          "ID": "2d67353d-9cfb-4169-94d6-4df2c5e3a8dd",
          "Name": "DefaultTraceCodeValue",
          "SQLName": "DefaultTraceCodeValue",
          "IsActive": "true"
        },
        {
          "ID": "4011aba1-93f3-41ab-ae2f-f6c7af50563a",
          "Name": "DefaultUnitValue",
          "SQLName": "DefaultUnitValue",
          "IsActive": "true"
        },
        {
          "ID": "be672e07-b3c6-492f-953a-40299b0ba0c9",
          "Name": "DenemeNX",
          "SQLName": "DenemeNX",
          "IsActive": "true"
        },
        {
          "ID": "b7039d36-bb20-45bf-b7e8-eb971d148b1f",
          "Name": "Description",
          "SQLName": "Description",
          "IsActive": "true"
        },
        {
          "ID": "f757699f-f4ba-4f4d-90e1-38dec0a645c7",
          "Name": "EndItem",
          "SQLName": "EndItem",
          "IsActive": "true"
        },
        {
          "ID": "05de8ab9-9e89-40e0-927e-89bf427a1a3d",
          "Name": "FolderLocation",
          "SQLName": "FolderLocation",
          "IsActive": "true"
        },
        {
          "ID": "529ef624-d68c-4e98-a716-a95273a69052",
          "Name": "FolderName",
          "SQLName": "FolderName",
          "IsActive": "true"
        },
        {
          "ID": "2125dfad-849b-4f84-b778-f17e9912c033",
          "Name": "GatheringPart",
          "SQLName": "GatheringPart",
          "IsActive": "true"
        },
        {
          "ID": "dd5990a9-9d7b-4acf-9f9f-1a208042af33",
          "Name": "GeneralStatus",
          "SQLName": "GeneralStatus",
          "IsActive": "true"
        },
        {
          "ID": "da0c4172-8a47-4995-b016-ebdecfd39933",
          "Name": "Identity",
          "SQLName": "Identity",
          "IsActive": "true"
        },
        {
          "ID": "f15b1d7c-3d73-499f-9db5-f60e2600f38d",
          "Name": "KaleKod",
          "SQLName": "KaleKod",
          "IsActive": "true"
        },
        {
          "ID": "76e05395-da92-44a1-a68d-eed8aa84b1ff",
          "Name": "Kaleargenumber",
          "SQLName": "Kaleargenumber",
          "IsActive": "true"
        },
        {
          "ID": "ef59adbf-536b-46ca-919f-2bfaf09d4c35",
          "Name": "Latest",
          "SQLName": "Latest",
          "IsActive": "true"
        },
        {
          "ID": "a67614b3-fd7a-4aa2-bdad-ea237828be1a",
          "Name": "Length",
          "SQLName": "Length",
          "IsActive": "true"
        },
        {
          "ID": "e81c7305-c59f-4689-bbed-cd696c170b2c",
          "Name": "LifeCycleTemplateName",
          "SQLName": "LifeCycleTemplateName",
          "IsActive": "true"
        },
        {
          "ID": "f36b6367-9dd8-47a1-a3a8-6ed400aa3e8f",
          "Name": "Mass",
          "SQLName": "Mass",
          "IsActive": "true"
        },
        {
          "ID": "c56f38dc-af78-4337-ad71-a481aa3514b5",
          "Name": "Material",
          "SQLName": "Material",
          "IsActive": "true"
        },
        {
          "ID": "4267259e-4b24-4115-b119-18e5245b2cfa",
          "Name": "ModifiedBy",
          "SQLName": "ModifiedBy",
          "IsActive": "true"
        },
        {
          "ID": "7438ce2f-41ee-4661-8def-976c1f835730",
          "Name": "NAME10",
          "SQLName": "NAME10",
          "IsActive": "true"
        },
        {
          "ID": "39e17223-253c-4f0f-aab6-1e182260e885",
          "Name": "NAME20",
          "SQLName": "NAME20",
          "IsActive": "true"
        },
        {
          "ID": "0457ae6e-4478-469f-845a-7410fff9976b",
          "Name": "NAME201@PTC.MultipleAliasAttributeValues",
          "SQLName": "NAME201@PTC.MultipleAliasAttributeValues",
          "IsActive": "true"
        },
        {
          "ID": "97300cda-5b78-4c4f-a7d0-0391984917b7",
          "Name": "NAME201",
          "SQLName": "NAME201",
          "IsActive": "true"
        },
        {
          "ID": "bc937eab-74cf-4771-aa95-e67fffc3d846",
          "Name": "Name",
          "SQLName": "Name",
          "IsActive": "true"
        },
        {
          "ID": "0e876412-b6c9-4fc6-8848-d8adad8746df",
          "Name": "Name30",
          "SQLName": "Name30",
          "IsActive": "true"
        },
        {
          "ID": "da1f78f6-fbec-4529-ae4d-9042806519ea",
          "Name": "Number",
          "SQLName": "Number",
          "IsActive": "true"
        },
        {
          "ID": "1a7eb5e4-b732-4e1a-a689-bfced2320ec0",
          "Name": "OEMPartSourcingStatus",
          "SQLName": "OEMPartSourcingStatus",
          "IsActive": "true"
        },
        {
          "ID": "d84c1d48-1049-4a28-8c09-5bee97b08676",
          "Name": "ObjectType",
          "SQLName": "ObjectType",
          "IsActive": "true"
        },
        {
          "ID": "87a1a84e-4580-4171-bb18-6233bf18b491",
          "Name": "OrganizationReference",
          "SQLName": "OrganizationReference",
          "IsActive": "true"
        },
        {
          "ID": "19a4029b-cb84-41a0-b478-afabde2efe4e",
          "Name": "PARCAADI",
          "SQLName": "PARCAADI",
          "IsActive": "true"
        },
        {
          "ID": "e7d87807-42f6-4755-a2ad-0a3c87536df0",
          "Name": "PTCWMNAME",
          "SQLName": "PTCWMNAME",
          "IsActive": "true"
        },
        {
          "ID": "f550a757-3872-4708-8f10-802b08a68830",
          "Name": "PhantomManufacturingPart",
          "SQLName": "PhantomManufacturingPart",
          "IsActive": "true"
        },
        {
          "ID": "5ed18f3d-d34d-4e55-ae35-efb67ad5ca4f",
          "Name": "Revision",
          "SQLName": "Revision",
          "IsActive": "true"
        },
        {
          "ID": "4b672c2e-4256-47a5-b167-50cff2b86544",
          "Name": "ShareStatus",
          "SQLName": "ShareStatus",
          "IsActive": "true"
        },
        {
          "ID": "fa3c89ae-a5f4-402d-aa91-ddcc9e8f66c9",
          "Name": "SourceValue",
          "SQLName": "SourceValue",
          "IsActive": "true"
        },
        {
          "ID": "5f52160e-9b0f-4c18-b225-565f1f5594fb",
          "Name": "SourceDuplicate",
          "SQLName": "SourceDuplicate",
          "IsActive": "true"
        },
        {
          "ID": "52dd571f-3c63-4a9a-bc0d-12f950c8c582",
          "Name": "Standard",
          "SQLName": "Standard",
          "IsActive": "true"
        },
        {
          "ID": "888dcb8d-ce00-4da4-b738-b91b68f53dda",
          "Name": "StateValue",
          "SQLName": "StateValue",
          "IsActive": "true"
        },
        {
          "ID": "9502ca70-b023-490e-ab7c-05ee5624786b",
          "Name": "Supersedes",
          "SQLName": "Supersedes",
          "IsActive": "true"
        },
        {
          "ID": "8a1ed16c-4520-456b-a1a0-1d6b5f92baa7",
          "Name": "Supplier",
          "SQLName": "Supplier",
          "IsActive": "true"
        },
        {
          "ID": "b7fd9eb8-3cee-4a1c-8848-92444cdbda7f",
          "Name": "TalepEden",
          "SQLName": "TalepEden",
          "IsActive": "true"
        },
        {
          "ID": "91caba0c-68ae-4934-a337-a4aa11b6f1af",
          "Name": "Thickness",
          "SQLName": "Thickness",
          "IsActive": "true"
        },
        {
          "ID": "44635dea-34c5-4153-be4a-3a7a4f5f66ba",
          "Name": "TypeIconPath",
          "SQLName": "TypeIconPath",
          "IsActive": "true"
        },
        {
          "ID": "b9815405-5b0a-4009-9e5a-677765bdcca6",
          "Name": "TypeIconTooltip",
          "SQLName": "TypeIconTooltip",
          "IsActive": "true"
        },
        {
          "ID": "965160eb-9398-4309-b3e7-da40ed67ace0",
          "Name": "UretimYeri",
          "SQLName": "UretimYeri",
          "IsActive": "true"
        },
        {
          "ID": "bd85ca9e-8e10-4bc2-b5bb-dc0a1816a71b",
          "Name": "Version",
          "SQLName": "Version",
          "IsActive": "true"
        },
        {
          "ID": "d723d4a8-73b7-4837-9d90-755ddecdf7d2",
          "Name": "VersionID",
          "SQLName": "VersionID",
          "IsActive": "true"
        },
        {
          "ID": "070f1458-3f3b-4020-8dd2-c0d04b442d61",
          "Name": "View",
          "SQLName": "View",
          "IsActive": "true"
        },
        {
          "ID": "aedf692e-bd48-4d16-bbdb-b8767d0b3484",
          "Name": "WorkInProgressStateValue",
          "SQLName": "WorkInProgressStateValue",
          "IsActive": "true"
        },
        {
          "ID": "333e20c1-1c32-40cd-be50-cb77cd86146e",
          "Name": "@PTC.AppliedContainerContext.LocalTimeZone",
          "SQLName": "@PTC.AppliedContainerContext.LocalTimeZone",
          "IsActive": "true"
        }
      ]
    },
    {
      "ID": "b3d7c901-e628-4d3b-893c-e4a51f85e04f",
      "Source_Api": "ProdMgmt/Parts('OR:wt.part.WTPart:",
      "State": "INWORK",
      "Api_adres": "http://localhost:7217/api",
      "Ana_kaynak": "PART",
      "Alt_endpoint": "INWORK",
      "sablonDataDurumu": "false",
      "sablonName": "PARTS - INWORK",
      "sablonData": [
        {
          "ID": "03bcd8de-274d-401b-9a5c-c44d9c7867b2",
          "Name": "source_Api",
          "SQLName": "source_Api",
          "IsActive": "ProdMgmt/Parts('OR:wt.part.WTPart:"
        },
        {
          "ID": "c2031728-2aa7-449a-95c4-48069649b4f0",
          "Name": "yapilacakIslem",
          "SQLName": "yapilacakIslem",
          "IsActive": "INWORK"
        },
        {
          "ID": "f3712da3-b571-42d4-bc1f-3cf3880dc130",
          "Name": "api_adres",
          "SQLName": "api_adres",
          "IsActive": "http://localhost:7217/api"
        },
        {
          "ID": "b51103df-c6f9-45c9-98a1-28ef601fb959",
          "Name": "ana_kaynak",
          "SQLName": "ana_kaynak",
          "IsActive": "PART"
        },
        {
          "ID": "75634924-5b48-461a-895c-e99549844835",
          "Name": "alt_endpoint",
          "SQLName": "alt_endpoint",
          "IsActive": "INWORK"
        },
        {
          "ID": "da98f56a-5b9b-439e-a82f-b255a4bbb1de",
          "Name": "CreatedOn",
          "SQLName": "CreatedOn",
          "IsActive": "true"
        },
        {
          "ID": "b10c1bcd-56e0-4eef-8b8d-cfee019f34a6",
          "Name": "ID",
          "SQLName": "ID",
          "IsActive": "true"
        },
        {
          "ID": "be505f56-0ea3-45be-82a0-29c37ea2a254",
          "Name": "LastModified",
          "SQLName": "LastModified",
          "IsActive": "true"
        },
        {
          "ID": "a707f252-3f08-4fca-9a1c-5875a47d7bca",
          "Name": "AlternateNumber",
          "SQLName": "AlternateNumber",
          "IsActive": "true"
        },
        {
          "ID": "7e2dae03-bdf6-48fe-a658-e1f44062bb16",
          "Name": "AssemblyModeValue",
          "SQLName": "AssemblyModeValue",
          "IsActive": "true"
        },
        {
          "ID": "3b47b6c6-2888-404a-b32c-b5fe5cfcc49c",
          "Name": "BOMType",
          "SQLName": "BOMType",
          "IsActive": "true"
        },
        {
          "ID": "404856e9-7f02-41e6-accc-967d3ebca080",
          "Name": "CADName",
          "SQLName": "CADName",
          "IsActive": "true"
        },
        {
          "ID": "1ddd61d6-5fb7-4449-8324-3f9f1306826e",
          "Name": "CLASSIFICATION",
          "SQLName": "CLASSIFICATION",
          "IsActive": "true"
        },
        {
          "ID": "91343f4c-4350-4009-8fef-9ac69458aa88",
          "Name": "CabinetName",
          "SQLName": "CabinetName",
          "IsActive": "true"
        },
        {
          "ID": "da5f3c85-884a-4304-b834-617e90d4f4ab",
          "Name": "ChangeStatus",
          "SQLName": "ChangeStatus",
          "IsActive": "true"
        },
        {
          "ID": "8de1ec02-a705-49fb-8265-bd7cceda327f",
          "Name": "CheckOutStatus",
          "SQLName": "CheckOutStatus",
          "IsActive": "true"
        },
        {
          "ID": "95682cf9-6cff-43a3-b6d7-154cec31da47",
          "Name": "CheckoutState",
          "SQLName": "CheckoutState",
          "IsActive": "true"
        },
        {
          "ID": "ec2ff608-e5c5-4870-92ff-639273b97808",
          "Name": "Comments",
          "SQLName": "Comments",
          "IsActive": "true"
        },
        {
          "ID": "8342adcb-40be-4426-8fad-876774570dcc",
          "Name": "ComponentType",
          "SQLName": "ComponentType",
          "IsActive": "true"
        },
        {
          "ID": "3debcb4a-0163-44c6-a5a9-669b51ac4698",
          "Name": "ConfigurableModuleValue",
          "SQLName": "ConfigurableModuleValue",
          "IsActive": "true"
        },
        {
          "ID": "af3e76ba-8126-413e-a29a-fe2b446199c9",
          "Name": "CreatedBy",
          "SQLName": "CreatedBy",
          "IsActive": "true"
        },
        {
          "ID": "4715a285-67c5-4f0d-9a80-b3fc7da86e49",
          "Name": "DefaultTraceCodeValue",
          "SQLName": "DefaultTraceCodeValue",
          "IsActive": "true"
        },
        {
          "ID": "585167c6-e63c-463d-a090-1e25f70fa5a0",
          "Name": "DefaultUnitValue",
          "SQLName": "DefaultUnitValue",
          "IsActive": "true"
        },
        {
          "ID": "c48d9918-df83-42aa-89ce-15017da33de7",
          "Name": "DenemeNX",
          "SQLName": "DenemeNX",
          "IsActive": "true"
        },
        {
          "ID": "191e9f95-59b6-4e1d-818d-47e421d876a4",
          "Name": "Description",
          "SQLName": "Description",
          "IsActive": "true"
        },
        {
          "ID": "f5243827-9111-4e50-9a54-19b8a0efde3c",
          "Name": "EndItem",
          "SQLName": "EndItem",
          "IsActive": "true"
        },
        {
          "ID": "8b8e695a-3f8a-40fe-9579-6fb75b9e6cda",
          "Name": "FolderLocation",
          "SQLName": "FolderLocation",
          "IsActive": "true"
        },
        {
          "ID": "eeb3bb1a-8548-4252-b83a-ae507138a343",
          "Name": "FolderName",
          "SQLName": "FolderName",
          "IsActive": "true"
        },
        {
          "ID": "09ff0757-7950-4725-af7f-f75f3c734288",
          "Name": "GatheringPart",
          "SQLName": "GatheringPart",
          "IsActive": "true"
        },
        {
          "ID": "b69d14c4-f1f3-4672-95c0-d957524a25d4",
          "Name": "GeneralStatus",
          "SQLName": "GeneralStatus",
          "IsActive": "true"
        },
        {
          "ID": "3929be48-d3c1-4915-a301-c90da0df6ec3",
          "Name": "Identity",
          "SQLName": "Identity",
          "IsActive": "true"
        },
        {
          "ID": "73d9cd6b-892d-4c0d-a6cf-a26c1a565e3b",
          "Name": "KaleKod",
          "SQLName": "KaleKod",
          "IsActive": "true"
        },
        {
          "ID": "9413673c-987f-46a0-b0ed-14a19f7adf59",
          "Name": "Kaleargenumber",
          "SQLName": "Kaleargenumber",
          "IsActive": "true"
        },
        {
          "ID": "16374368-464e-4dfc-b126-73a481cec7a2",
          "Name": "Latest",
          "SQLName": "Latest",
          "IsActive": "true"
        },
        {
          "ID": "41ceb6ca-c0ab-4814-b095-0be22a109236",
          "Name": "Length",
          "SQLName": "Length",
          "IsActive": "true"
        },
        {
          "ID": "8610352e-d2f0-4183-b379-14e0e2452216",
          "Name": "LifeCycleTemplateName",
          "SQLName": "LifeCycleTemplateName",
          "IsActive": "true"
        },
        {
          "ID": "5e028f41-c792-439e-8884-7537ac564027",
          "Name": "Mass",
          "SQLName": "Mass",
          "IsActive": "true"
        },
        {
          "ID": "c71f3350-b06f-42b9-b626-6dbedaf44ce5",
          "Name": "Material",
          "SQLName": "Material",
          "IsActive": "true"
        },
        {
          "ID": "bc4e79bf-ef1b-43af-b6c2-8e3deaac0e29",
          "Name": "ModifiedBy",
          "SQLName": "ModifiedBy",
          "IsActive": "true"
        },
        {
          "ID": "f3ffe77f-4b04-407f-916b-18bd0b7a3293",
          "Name": "NAME10",
          "SQLName": "NAME10",
          "IsActive": "true"
        },
        {
          "ID": "427943b4-abb9-4a43-a6b9-9bc41602458d",
          "Name": "NAME20",
          "SQLName": "NAME20",
          "IsActive": "true"
        },
        {
          "ID": "4216ec2b-3d26-4d1a-b8af-06f9f6fc244f",
          "Name": "NAME201@PTC.MultipleAliasAttributeValues",
          "SQLName": "NAME201@PTC.MultipleAliasAttributeValues",
          "IsActive": "true"
        },
        {
          "ID": "8dcef4b4-9795-4144-90d6-8addb57a47cf",
          "Name": "NAME201",
          "SQLName": "NAME201",
          "IsActive": "true"
        },
        {
          "ID": "3481fb8e-5f6f-4088-9d7f-c7cc0ecaddbc",
          "Name": "Name",
          "SQLName": "Name",
          "IsActive": "true"
        },
        {
          "ID": "10d74e79-185f-4620-a0f5-3e45fb548989",
          "Name": "Name30",
          "SQLName": "Name30",
          "IsActive": "true"
        },
        {
          "ID": "46959a41-c93d-4ac7-8742-b825645cf0c2",
          "Name": "Number",
          "SQLName": "Number",
          "IsActive": "true"
        },
        {
          "ID": "397a48ef-5ebe-4a6f-9cbf-7d044c95b481",
          "Name": "OEMPartSourcingStatus",
          "SQLName": "OEMPartSourcingStatus",
          "IsActive": "true"
        },
        {
          "ID": "77f0b477-d75b-4c03-a8c2-96c96e6ac0da",
          "Name": "ObjectType",
          "SQLName": "ObjectType",
          "IsActive": "true"
        },
        {
          "ID": "44dbc033-0bdd-4802-a3e1-f941efa3cf75",
          "Name": "OrganizationReference",
          "SQLName": "OrganizationReference",
          "IsActive": "true"
        },
        {
          "ID": "c2f43e90-f289-4407-a7d3-339d39647a2f",
          "Name": "PARCAADI",
          "SQLName": "PARCAADI",
          "IsActive": "true"
        },
        {
          "ID": "afad7090-75bd-4b95-9854-658b9870dabb",
          "Name": "PTCWMNAME",
          "SQLName": "PTCWMNAME",
          "IsActive": "true"
        },
        {
          "ID": "4891efc1-b7ca-4447-8361-27acf1372403",
          "Name": "PhantomManufacturingPart",
          "SQLName": "PhantomManufacturingPart",
          "IsActive": "true"
        },
        {
          "ID": "a2b87470-a660-4712-958f-5c864617d8bb",
          "Name": "Revision",
          "SQLName": "Revision",
          "IsActive": "true"
        },
        {
          "ID": "859afe4d-df3e-4d2d-a539-a5b88bca1be8",
          "Name": "ShareStatus",
          "SQLName": "ShareStatus",
          "IsActive": "true"
        },
        {
          "ID": "c2abc0d9-250c-46ac-b83c-9224bcc1fc7c",
          "Name": "SourceValue",
          "SQLName": "SourceValue",
          "IsActive": "true"
        },
        {
          "ID": "c1441a7d-8ce1-4f70-9183-caeb44e08a2d",
          "Name": "SourceDuplicate",
          "SQLName": "SourceDuplicate",
          "IsActive": "true"
        },
        {
          "ID": "f4c5277a-664d-461e-89f3-ffca3163a4e2",
          "Name": "Standard",
          "SQLName": "Standard",
          "IsActive": "true"
        },
        {
          "ID": "525e0f41-887b-4130-989f-f4fe9e5a91da",
          "Name": "StateValue",
          "SQLName": "StateValue",
          "IsActive": "true"
        },
        {
          "ID": "05724b8d-4999-4b07-a436-ee57191e4421",
          "Name": "Supersedes",
          "SQLName": "Supersedes",
          "IsActive": "true"
        },
        {
          "ID": "22036b1e-b6d4-44fa-8a74-3d1f19e29163",
          "Name": "Supplier",
          "SQLName": "Supplier",
          "IsActive": "true"
        },
        {
          "ID": "44c2fbdd-5ad4-4e2a-81d7-6334fc6bd186",
          "Name": "TalepEden",
          "SQLName": "TalepEden",
          "IsActive": "true"
        },
        {
          "ID": "7acf1626-d952-4f7b-b8e7-0ce9f526c85c",
          "Name": "Thickness",
          "SQLName": "Thickness",
          "IsActive": "true"
        },
        {
          "ID": "245c1f22-101b-4c00-9d69-48eb8ac0e3f7",
          "Name": "TypeIconPath",
          "SQLName": "TypeIconPath",
          "IsActive": "true"
        },
        {
          "ID": "679c3da3-2aeb-400b-b4f7-26cb1229b083",
          "Name": "TypeIconTooltip",
          "SQLName": "TypeIconTooltip",
          "IsActive": "true"
        },
        {
          "ID": "52f79368-1c81-446a-89aa-2166a8881f28",
          "Name": "UretimYeri",
          "SQLName": "UretimYeri",
          "IsActive": "true"
        },
        {
          "ID": "dc11fcc4-31bd-4479-9e89-5deb123f7ded",
          "Name": "Version",
          "SQLName": "Version",
          "IsActive": "true"
        },
        {
          "ID": "335678c9-954e-4fd5-908d-43369e097c1f",
          "Name": "VersionID",
          "SQLName": "VersionID",
          "IsActive": "true"
        },
        {
          "ID": "fb284ea2-3b13-4c85-bbb4-a1e9795c71f7",
          "Name": "View",
          "SQLName": "View",
          "IsActive": "true"
        },
        {
          "ID": "19723cb8-ae59-4a23-a74f-176d6a0a59c3",
          "Name": "WorkInProgressStateValue",
          "SQLName": "WorkInProgressStateValue",
          "IsActive": "true"
        },
        {
          "ID": "af6adf30-3c58-4dfb-8452-ffa5b7772e24",
          "Name": "@PTC.AppliedContainerContext.LocalTimeZone",
          "SQLName": "@PTC.AppliedContainerContext.LocalTimeZone",
          "IsActive": "true"
        }
      ]
    },
    {
      "ID": "36a3fbe1-aff7-4a30-b10e-9ee957fe9ab8",
      "Source_Api": "ProdMgmt/Parts('OR:wt.part.WTPart:",
      "State": "CANCELLED",
      "Api_adres": "http://localhost:7217/api",
      "Ana_kaynak": "PART",
      "Alt_endpoint": "CANCELLED",
      "sablonDataDurumu": "true",
      "sablonName": "PARTS - CANCELLED",
      "sablonData": [
        {
          "ID": "c0e71de4-5fa0-465b-9444-99c1a9c380e2",
          "Name": "source_Api",
          "SQLName": "source_Api",
          "IsActive": "ProdMgmt/Parts('OR:wt.part.WTPart:"
        },
        {
          "ID": "100d58a4-0b87-4651-b564-72af1c836d16",
          "Name": "yapilacakIslem",
          "SQLName": "yapilacakIslem",
          "IsActive": "CANCELLED"
        },
        {
          "ID": "d321f087-d0ef-4f2f-888b-bb6edf5b7ef5",
          "Name": "api_adres",
          "SQLName": "api_adres",
          "IsActive": "http://localhost:7217/api"
        },
        {
          "ID": "d8514aff-4e54-437c-8759-ebc76b876b34",
          "Name": "ana_kaynak",
          "SQLName": "ana_kaynak",
          "IsActive": "PART"
        },
        {
          "ID": "948bbf84-57c3-4711-9802-a0ccef9d59cf",
          "Name": "alt_endpoint",
          "SQLName": "alt_endpoint",
          "IsActive": "CANCELLED"
        },
        {
          "ID": "6fe9421b-f796-4b06-9be6-6e7daf8a1893",
          "Name": "CreatedOn",
          "SQLName": "CreatedOn",
          "IsActive": "true"
        },
        {
          "ID": "bbda01bf-40ce-468e-997e-b75ed0ed0bc6",
          "Name": "ID",
          "SQLName": "ID",
          "IsActive": "true"
        },
        {
          "ID": "f9b33249-f4ea-467b-b735-be4a1f2329c7",
          "Name": "LastModified",
          "SQLName": "LastModified",
          "IsActive": "true"
        },
        {
          "ID": "bf15e061-d21d-44fc-a94b-a0e4732eda95",
          "Name": "AlternateNumber",
          "SQLName": "AlternateNumber",
          "IsActive": "true"
        },
        {
          "ID": "1eaf6dfa-b82d-433e-8514-f090e320a3f2",
          "Name": "AssemblyModeValue",
          "SQLName": "AssemblyModeValue",
          "IsActive": "true"
        },
        {
          "ID": "a27268fb-a91a-45b1-a113-0abf48ef12c4",
          "Name": "BOMType",
          "SQLName": "BOMType",
          "IsActive": "true"
        },
        {
          "ID": "c24d2475-fb15-43a5-93f0-f4c468c5a560",
          "Name": "CADName",
          "SQLName": "CADName",
          "IsActive": "true"
        },
        {
          "ID": "9dbf21f4-f172-4e9b-9aae-e544c2f2aedd",
          "Name": "CLASSIFICATION",
          "SQLName": "CLASSIFICATION",
          "IsActive": "true"
        },
        {
          "ID": "5db07789-0093-4769-b0f1-2ded5a1d9520",
          "Name": "CabinetName",
          "SQLName": "CabinetName",
          "IsActive": "true"
        },
        {
          "ID": "fc889ec7-09d2-4a37-adad-1858af94287f",
          "Name": "ChangeStatus",
          "SQLName": "ChangeStatus",
          "IsActive": "true"
        },
        {
          "ID": "d7915cb9-622c-455b-bf29-79b275a9d10e",
          "Name": "CheckOutStatus",
          "SQLName": "CheckOutStatus",
          "IsActive": "true"
        },
        {
          "ID": "01002db7-964c-4c10-987c-7253a565da12",
          "Name": "CheckoutState",
          "SQLName": "CheckoutState",
          "IsActive": "true"
        },
        {
          "ID": "914886f7-3387-499f-a65e-989f922c4581",
          "Name": "Comments",
          "SQLName": "Comments",
          "IsActive": "true"
        },
        {
          "ID": "b589a4f4-b254-41d3-a1dd-81dfe1f4dae2",
          "Name": "ComponentType",
          "SQLName": "ComponentType",
          "IsActive": "true"
        },
        {
          "ID": "7a897099-76b8-4cfb-942a-ee03589c3fcb",
          "Name": "ConfigurableModuleValue",
          "SQLName": "ConfigurableModuleValue",
          "IsActive": "true"
        },
        {
          "ID": "e6a92898-a816-4d29-bc0d-ff811998b537",
          "Name": "CreatedBy",
          "SQLName": "CreatedBy",
          "IsActive": "true"
        },
        {
          "ID": "94638d4a-d619-4e16-8f1e-a93b426eeb3a",
          "Name": "DefaultTraceCodeValue",
          "SQLName": "DefaultTraceCodeValue",
          "IsActive": "true"
        },
        {
          "ID": "83f92bef-9480-4edb-88ab-44e8c0083a1a",
          "Name": "DefaultUnitValue",
          "SQLName": "DefaultUnitValue",
          "IsActive": "true"
        },
        {
          "ID": "0fcfad21-2eaf-4f3e-9b87-b345659a8d07",
          "Name": "DenemeNX",
          "SQLName": "DenemeNX",
          "IsActive": "true"
        },
        {
          "ID": "48464c62-b9e5-458a-965e-e854b90e24e4",
          "Name": "Description",
          "SQLName": "Description",
          "IsActive": "true"
        },
        {
          "ID": "ab38649f-5921-4f65-a5e9-21f2a4d2befe",
          "Name": "EndItem",
          "SQLName": "EndItem",
          "IsActive": "true"
        },
        {
          "ID": "d84c438b-36b7-4faa-96e7-e60e144cbd81",
          "Name": "FolderLocation",
          "SQLName": "FolderLocation",
          "IsActive": "true"
        },
        {
          "ID": "0cde933c-1242-4dc3-a614-a335fe111ce9",
          "Name": "FolderName",
          "SQLName": "FolderName",
          "IsActive": "true"
        },
        {
          "ID": "106d389a-47f5-4c39-b912-8c68ce28afad",
          "Name": "GatheringPart",
          "SQLName": "GatheringPart",
          "IsActive": "true"
        },
        {
          "ID": "cc8b0054-dc20-4189-bf89-6285bfc38226",
          "Name": "GeneralStatus",
          "SQLName": "GeneralStatus",
          "IsActive": "true"
        },
        {
          "ID": "9e78046a-3f8d-44d2-b730-30c56224af0b",
          "Name": "Identity",
          "SQLName": "Identity",
          "IsActive": "true"
        },
        {
          "ID": "0fc77615-6015-4a7c-ad98-d9006a856eb0",
          "Name": "KaleKod",
          "SQLName": "KaleKod",
          "IsActive": "true"
        },
        {
          "ID": "ee61f30e-0822-4444-8c64-f7c5b8c4eeb4",
          "Name": "Kaleargenumber",
          "SQLName": "Kaleargenumber",
          "IsActive": "true"
        },
        {
          "ID": "abc9d245-aa4c-4498-b146-05fbdf9049a6",
          "Name": "Latest",
          "SQLName": "Latest",
          "IsActive": "true"
        },
        {
          "ID": "f8b32344-bab1-4420-9e6e-9aafce565371",
          "Name": "Length",
          "SQLName": "Length",
          "IsActive": "true"
        },
        {
          "ID": "165fcfb1-2f7c-43e7-a18e-0e1a3010cb78",
          "Name": "LifeCycleTemplateName",
          "SQLName": "LifeCycleTemplateName",
          "IsActive": "true"
        },
        {
          "ID": "48023b2b-acf0-4bb9-880b-e6263f874011",
          "Name": "Mass",
          "SQLName": "Mass",
          "IsActive": "true"
        },
        {
          "ID": "4b4dca9e-4e31-4930-a4b7-0ccdb7524df5",
          "Name": "Material",
          "SQLName": "Material",
          "IsActive": "true"
        },
        {
          "ID": "eb20803e-83ad-400b-96d6-b696fa4f011a",
          "Name": "ModifiedBy",
          "SQLName": "ModifiedBy",
          "IsActive": "true"
        },
        {
          "ID": "806b8d00-0c7e-4562-bcf4-7469b3826a56",
          "Name": "NAME10",
          "SQLName": "NAME10",
          "IsActive": "true"
        },
        {
          "ID": "f48375a7-1d3d-48a3-a41a-0d0659863766",
          "Name": "NAME20",
          "SQLName": "NAME20",
          "IsActive": "true"
        },
        {
          "ID": "042407b0-3c1e-40ab-af99-a15487e90052",
          "Name": "NAME201@PTC.MultipleAliasAttributeValues",
          "SQLName": "NAME201@PTC.MultipleAliasAttributeValues",
          "IsActive": "true"
        },
        {
          "ID": "7a487433-dd82-40fd-8bbb-fe3c30808915",
          "Name": "NAME201",
          "SQLName": "NAME201",
          "IsActive": "true"
        },
        {
          "ID": "426c8bea-f4a8-487d-811d-e325ddf35c51",
          "Name": "Name",
          "SQLName": "Name",
          "IsActive": "true"
        },
        {
          "ID": "a222dd99-acff-42b3-a544-2f2d8c195563",
          "Name": "Name30",
          "SQLName": "Name30",
          "IsActive": "true"
        },
        {
          "ID": "1c0746ec-0abc-434b-8107-babf7a117644",
          "Name": "Number",
          "SQLName": "Number",
          "IsActive": "true"
        },
        {
          "ID": "a7bfc3bb-b6e7-4c4d-b5ff-0350bedca825",
          "Name": "OEMPartSourcingStatus",
          "SQLName": "OEMPartSourcingStatus",
          "IsActive": "true"
        },
        {
          "ID": "2adf2b2e-20bc-4224-a511-f1371e00f6bc",
          "Name": "ObjectType",
          "SQLName": "ObjectType",
          "IsActive": "true"
        },
        {
          "ID": "ead023e3-6f47-4e19-95f0-fb69f2317c45",
          "Name": "OrganizationReference",
          "SQLName": "OrganizationReference",
          "IsActive": "true"
        },
        {
          "ID": "cc7a4c21-c3d0-4bdf-86ae-88dae4e0ad11",
          "Name": "PARCAADI",
          "SQLName": "PARCAADI",
          "IsActive": "true"
        },
        {
          "ID": "4d687cb4-1e51-43db-9a74-89f84029d3b7",
          "Name": "PTCWMNAME",
          "SQLName": "PTCWMNAME",
          "IsActive": "true"
        },
        {
          "ID": "e43e09ce-0d46-42d8-a53b-f132d6d6f020",
          "Name": "PhantomManufacturingPart",
          "SQLName": "PhantomManufacturingPart",
          "IsActive": "true"
        },
        {
          "ID": "1fadfe9a-0a5b-4e59-9413-c6ad9d3f6a3f",
          "Name": "Revision",
          "SQLName": "Revision",
          "IsActive": "true"
        },
        {
          "ID": "3a9c08f5-f9aa-4c2a-ab42-d3b224975096",
          "Name": "ShareStatus",
          "SQLName": "ShareStatus",
          "IsActive": "true"
        },
        {
          "ID": "1a77aef2-9687-465c-a915-c17535ad9e30",
          "Name": "SourceValue",
          "SQLName": "SourceValue",
          "IsActive": "true"
        },
        {
          "ID": "58364e4c-d48f-4e5a-9539-2bbb9d57a9b9",
          "Name": "SourceDuplicate",
          "SQLName": "SourceDuplicate",
          "IsActive": "true"
        },
        {
          "ID": "6d8d83a8-cece-4fff-bd4f-5586ba13d5dc",
          "Name": "Standard",
          "SQLName": "Standard",
          "IsActive": "true"
        },
        {
          "ID": "b4f7d818-5429-4cc4-8508-aab826102042",
          "Name": "StateValue",
          "SQLName": "StateValue",
          "IsActive": "true"
        },
        {
          "ID": "65bddcfc-72f9-44af-ae37-d915e3813b94",
          "Name": "Supersedes",
          "SQLName": "Supersedes",
          "IsActive": "true"
        },
        {
          "ID": "126446cd-d33e-4c52-a329-f7dfba39dc59",
          "Name": "Supplier",
          "SQLName": "Supplier",
          "IsActive": "true"
        },
        {
          "ID": "9e5f5ac6-1a42-45c8-996e-f2d219ef50be",
          "Name": "TalepEden",
          "SQLName": "TalepEden",
          "IsActive": "true"
        },
        {
          "ID": "9392c76c-7d38-41c6-bb64-19c98da4233a",
          "Name": "Thickness",
          "SQLName": "Thickness",
          "IsActive": "true"
        },
        {
          "ID": "4dd965a2-6ef6-4b81-9d19-aab594dfb3df",
          "Name": "TypeIconPath",
          "SQLName": "TypeIconPath",
          "IsActive": "true"
        },
        {
          "ID": "8b7e7a47-afc4-469b-a60a-858ff0e03504",
          "Name": "TypeIconTooltip",
          "SQLName": "TypeIconTooltip",
          "IsActive": "true"
        },
        {
          "ID": "c3fd7378-d904-4852-b7ed-7b2f752f08de",
          "Name": "UretimYeri",
          "SQLName": "UretimYeri",
          "IsActive": "true"
        },
        {
          "ID": "ac381a0b-eef2-4d77-b771-7e986f04d482",
          "Name": "Version",
          "SQLName": "Version",
          "IsActive": "true"
        },
        {
          "ID": "7bef3073-048f-4e03-9592-9409b3b50838",
          "Name": "VersionID",
          "SQLName": "VersionID",
          "IsActive": "true"
        },
        {
          "ID": "9021c4e1-70a7-4927-a837-4407a9873b77",
          "Name": "View",
          "SQLName": "View",
          "IsActive": "true"
        },
        {
          "ID": "d92eb2b4-8fb6-4ada-a0c7-979f9c7a006d",
          "Name": "WorkInProgressStateValue",
          "SQLName": "WorkInProgressStateValue",
          "IsActive": "true"
        },
        {
          "ID": "4a39b245-6124-4590-b1b4-8e72294df97f",
          "Name": "@PTC.AppliedContainerContext.LocalTimeZone",
          "SQLName": "@PTC.AppliedContainerContext.LocalTimeZone",
          "IsActive": "true"
        }
      ]
    },
    {
      "ID": "9b8a874c-c297-40c9-b81a-056881a987c1",
      "Source_Api": "CADDocumentMgmt/CADDocuments('OR:wt.epm.EPMDocument:",
      "State": "RELEASED",
      "Api_adres": "http://localhost:7217/api",
      "Ana_kaynak": "CAD",
      "Alt_endpoint": "RELEASED_CAD",
      "sablonDataDurumu": "true",
      "sablonName": "CADDocuments - RELEASED",
      "sablonData": [
        {
          "ID": "08e28d51-40c0-41bf-83bc-de6a12bb5a3e",
          "Name": "source_Api",
          "SQLName": "source_Api",
          "IsActive": "CADDocumentMgmt/CADDocuments('OR:wt.epm.EPMDocument:"
        },
        {
          "ID": "a37aa29a-966c-4a3e-8fcc-0f068a026f59",
          "Name": "yapilacakIslem",
          "SQLName": "yapilacakIslem",
          "IsActive": "RELEASED"
        },
        {
          "ID": "8fe43f63-636c-4efa-af8a-363ac9d42e05",
          "Name": "api_adres",
          "SQLName": "api_adres",
          "IsActive": "http://localhost:7217/api"
        },
        {
          "ID": "9caffac7-9510-472d-973c-a56568ae052c",
          "Name": "ana_kaynak",
          "SQLName": "ana_kaynak",
          "IsActive": "CAD"
        },
        {
          "ID": "52454041-1de9-4614-99af-348908ef5053",
          "Name": "alt_endpoint",
          "SQLName": "alt_endpoint",
          "IsActive": "RELEASED_CAD"
        },
        {
          "ID": "e2819e2a-6427-4d0d-8401-2155debd64f7",
          "Name": "CreatedOn",
          "SQLName": "CreatedOn",
          "IsActive": "true"
        },
        {
          "ID": "8a1c3391-5991-44d4-a289-0f1b1daa723c",
          "Name": "ID",
          "SQLName": "ID",
          "IsActive": "true"
        },
        {
          "ID": "58b8f301-8698-493f-92ae-757f6d443470",
          "Name": "LastModified",
          "SQLName": "LastModified",
          "IsActive": "true"
        },
        {
          "ID": "02653cb4-a749-41c9-b932-ff2a35bb6474",
          "Name": "AuthAppVersion",
          "SQLName": "AuthAppVersion",
          "IsActive": "true"
        },
        {
          "ID": "5e77ce53-5e69-4ffa-b0b2-c3c4aa163955",
          "Name": "AuthoringApplication",
          "SQLName": "AuthoringApplication",
          "IsActive": "true"
        },
        {
          "ID": "d816571a-aa93-43dc-bf70-d951aab2cfdf",
          "Name": "CabinetName",
          "SQLName": "CabinetName",
          "IsActive": "true"
        },
        {
          "ID": "3c280b50-4411-48b4-ab5e-76bc14f65794",
          "Name": "Category",
          "SQLName": "Category",
          "IsActive": "true"
        },
        {
          "ID": "8fdd4dc1-18ca-4bde-97d9-dbba6d7cbc14",
          "Name": "ChangeStatus",
          "SQLName": "ChangeStatus",
          "IsActive": "true"
        },
        {
          "ID": "c15c81f0-12df-4c5a-b1dc-7cfc15a9e568",
          "Name": "CheckOutStatus",
          "SQLName": "CheckOutStatus",
          "IsActive": "true"
        },
        {
          "ID": "2ec6b30a-8584-433c-8815-3caf4972a3eb",
          "Name": "CheckoutState",
          "SQLName": "CheckoutState",
          "IsActive": "true"
        },
        {
          "ID": "edc74c90-38c7-4bad-a668-5d3a387dabad",
          "Name": "Comments",
          "SQLName": "Comments",
          "IsActive": "true"
        },
        {
          "ID": "80b717b8-8caa-41dd-bbad-46ca7e352ea3",
          "Name": "ComponentType",
          "SQLName": "ComponentType",
          "IsActive": "true"
        },
        {
          "ID": "2a34aac5-b499-4c00-ba8b-9b59775a45ce",
          "Name": "CreatedBy",
          "SQLName": "CreatedBy",
          "IsActive": "true"
        },
        {
          "ID": "f9537067-7fb9-4a08-99e9-7029c3e05376",
          "Name": "DenemeNX",
          "SQLName": "DenemeNX",
          "IsActive": "true"
        },
        {
          "ID": "691def2d-5013-4458-a883-809d0b99ce1f",
          "Name": "Derived",
          "SQLName": "Derived",
          "IsActive": "true"
        },
        {
          "ID": "4d94d80f-a52e-47c4-9114-abcbf31a0254",
          "Name": "Description",
          "SQLName": "Description",
          "IsActive": "true"
        },
        {
          "ID": "a3164604-d354-43da-8e30-20c8bf27c21e",
          "Name": "FamilyTableStatus",
          "SQLName": "FamilyTableStatus",
          "IsActive": "true"
        },
        {
          "ID": "86ff8069-d3b0-4a20-a5a7-b83063775564",
          "Name": "FileName",
          "SQLName": "FileName",
          "IsActive": "true"
        },
        {
          "ID": "dd14f3dd-be41-4680-b13c-93a3ed537aa5",
          "Name": "FolderLocation",
          "SQLName": "FolderLocation",
          "IsActive": "true"
        },
        {
          "ID": "2417c215-877a-454a-98cd-1423430d854a",
          "Name": "FolderName",
          "SQLName": "FolderName",
          "IsActive": "true"
        },
        {
          "ID": "d20fb148-7173-4045-8f11-a5e2f5f047d1",
          "Name": "GeneralStatus",
          "SQLName": "GeneralStatus",
          "IsActive": "true"
        },
        {
          "ID": "f23cb34b-d88c-4187-bd86-d6dced98c0b2",
          "Name": "Generic",
          "SQLName": "Generic",
          "IsActive": "true"
        },
        {
          "ID": "06cf86e6-4bb6-42a9-888c-2db3eef7153b",
          "Name": "Identity",
          "SQLName": "Identity",
          "IsActive": "true"
        },
        {
          "ID": "c809a774-9532-4d3c-acb2-773b802c2e5f",
          "Name": "Instance",
          "SQLName": "Instance",
          "IsActive": "true"
        },
        {
          "ID": "c82c7ba4-7bbd-46da-bfb8-3cc7d5a1abc7",
          "Name": "Kaleargenumber",
          "SQLName": "Kaleargenumber",
          "IsActive": "true"
        },
        {
          "ID": "a577bb8d-8ac9-4178-94e3-17dc76fcabbb",
          "Name": "Latest",
          "SQLName": "Latest",
          "IsActive": "true"
        },
        {
          "ID": "6b6bf24d-26e5-4af0-8e3d-a70a0960a8ab",
          "Name": "Length",
          "SQLName": "Length",
          "IsActive": "true"
        },
        {
          "ID": "4f9670fe-b131-429e-91b4-204a2e0ce33c",
          "Name": "LifeCycleTemplateName",
          "SQLName": "LifeCycleTemplateName",
          "IsActive": "true"
        },
        {
          "ID": "97832125-137a-488c-b97e-3fb008361a64",
          "Name": "Mass",
          "SQLName": "Mass",
          "IsActive": "true"
        },
        {
          "ID": "9eda0e1a-e789-4931-8eeb-254162b18469",
          "Name": "Mass1",
          "SQLName": "Mass1",
          "IsActive": "true"
        },
        {
          "ID": "d7d5af09-1b81-47a6-88da-fee64bcbb947",
          "Name": "Mass11",
          "SQLName": "Mass11",
          "IsActive": "true"
        },
        {
          "ID": "b7532b9e-f08e-48a5-b924-ce0a44e9d5cc",
          "Name": "MassTest",
          "SQLName": "MassTest",
          "IsActive": "true"
        },
        {
          "ID": "52e37fe8-8ebb-4308-81fe-97144e591bb3",
          "Name": "Material",
          "SQLName": "Material",
          "IsActive": "true"
        },
        {
          "ID": "8c512263-0123-4565-83fb-365f13506333",
          "Name": "MissingDependents",
          "SQLName": "MissingDependents",
          "IsActive": "true"
        },
        {
          "ID": "86964bef-e431-4ccf-baad-3e48c61f6cca",
          "Name": "ModifiedBy",
          "SQLName": "ModifiedBy",
          "IsActive": "true"
        },
        {
          "ID": "3e2d6c94-c568-4f5a-99e4-23aedb1c0ab8",
          "Name": "NAME10",
          "SQLName": "NAME10",
          "IsActive": "true"
        },
        {
          "ID": "f6bef8a1-bb86-425a-8026-9a13c735c9a2",
          "Name": "NAME30",
          "SQLName": "NAME30",
          "IsActive": "true"
        },
        {
          "ID": "5a392982-67ea-4afa-a341-7a3470a204ba",
          "Name": "NDVersion",
          "SQLName": "NDVersion",
          "IsActive": "true"
        },
        {
          "ID": "341aa0e2-8b83-48ac-b925-adca7148b01b",
          "Name": "Name",
          "SQLName": "Name",
          "IsActive": "true"
        },
        {
          "ID": "149b290e-d820-4501-84c3-28b181740f85",
          "Name": "Number",
          "SQLName": "Number",
          "IsActive": "true"
        },
        {
          "ID": "3818ca64-afd0-45b9-a610-bfcea15db10d",
          "Name": "ObjectType",
          "SQLName": "ObjectType",
          "IsActive": "true"
        },
        {
          "ID": "ac373dc6-1670-476b-a35f-a95aec9ac954",
          "Name": "OrganizationReference",
          "SQLName": "OrganizationReference",
          "IsActive": "true"
        },
        {
          "ID": "87150319-a3f1-4978-98c0-899f02c53211",
          "Name": "OwnerApplication",
          "SQLName": "OwnerApplication",
          "IsActive": "true"
        },
        {
          "ID": "be6c9110-005f-4009-9588-1b13173244d7",
          "Name": "PARCAADI",
          "SQLName": "PARCAADI",
          "IsActive": "true"
        },
        {
          "ID": "35521d59-5600-4adf-a25f-e5722f2373a9",
          "Name": "Revision",
          "SQLName": "Revision",
          "IsActive": "true"
        },
        {
          "ID": "89b3c580-0b0f-45da-8990-2b70d72082bc",
          "Name": "ShareStatus",
          "SQLName": "ShareStatus",
          "IsActive": "true"
        },
        {
          "ID": "046da4ac-6f5d-458c-826a-20250a23cef4",
          "Name": "Source",
          "SQLName": "Source",
          "IsActive": "true"
        },
        {
          "ID": "6d5ec67c-3222-41f9-a8d4-6ecbc7fa2585",
          "Name": "Standard",
          "SQLName": "Standard",
          "IsActive": "true"
        },
        {
          "ID": "8fc41975-e976-4ba7-b91e-1c5ed3a0fefc",
          "Name": "Standard2",
          "SQLName": "Standard2",
          "IsActive": "true"
        },
        {
          "ID": "61bc4ae4-3528-4a51-85b3-3f447ad85b71",
          "Name": "State",
          "SQLName": "State",
          "IsActive": "true"
        },
        {
          "ID": "e5936e73-79bd-4a5b-84c4-3a24dac2d1ea",
          "Name": "SubCategory",
          "SQLName": "SubCategory",
          "IsActive": "true"
        },
        {
          "ID": "cc2a521b-2327-424c-8f79-5b674eef0140",
          "Name": "Supplier",
          "SQLName": "Supplier",
          "IsActive": "true"
        },
        {
          "ID": "626b4761-d167-4f23-9937-eaa8ba4c3fdc",
          "Name": "Thickness",
          "SQLName": "Thickness",
          "IsActive": "true"
        },
        {
          "ID": "893cbc2f-a46d-41d8-b67c-ce2af30d8f76",
          "Name": "TypeDisplayName",
          "SQLName": "TypeDisplayName",
          "IsActive": "true"
        },
        {
          "ID": "df4bae94-f089-4d3e-a3c0-4691e459b615",
          "Name": "TypeIcon",
          "SQLName": "TypeIcon",
          "IsActive": "true"
        },
        {
          "ID": "06386a48-beed-43fe-97ad-a66db69d252b",
          "Name": "Verified",
          "SQLName": "Verified",
          "IsActive": "true"
        },
        {
          "ID": "7b35f913-6464-4a6e-8dda-f0bd2767ded8",
          "Name": "Version",
          "SQLName": "Version",
          "IsActive": "true"
        },
        {
          "ID": "487c07d7-d3e9-4e3d-a14a-91f2599015e4",
          "Name": "VersionID",
          "SQLName": "VersionID",
          "IsActive": "true"
        },
        {
          "ID": "30fb63f3-9d85-4765-ab5f-937378db9036",
          "Name": "WorkInProgressState",
          "SQLName": "WorkInProgressState",
          "IsActive": "true"
        },
        {
          "ID": "6baf4526-0c94-4cc8-80c3-26b705066bac",
          "Name": "@PTC.AppliedContainerContext.LocalTimeZone",
          "SQLName": "@PTC.AppliedContainerContext.LocalTimeZone",
          "IsActive": "true"
        }
      ]
    },
    {
      "ID": "a2915a93-df37-4f8e-8728-8d1150ca5922",
      "Source_Api": "CADDocumentMgmt/CADDocuments('OR:wt.epm.EPMDocument:",
      "State": "CANCELLED",
      "Api_adres": "http://localhost:7217/api",
      "Ana_kaynak": "CAD",
      "Alt_endpoint": "CANCELLED_CAD",
      "sablonDataDurumu": "true",
      "sablonName": "CADDocuments - CANCELLED",
      "sablonData": [
        {
          "ID": "fe4a75b7-b79c-4907-89cd-5631ca7da127",
          "Name": "source_Api",
          "SQLName": "source_Api",
          "IsActive": "CADDocumentMgmt/CADDocuments('OR:wt.epm.EPMDocument:"
        },
        {
          "ID": "bb0363f8-22da-4a21-b73c-b3f9e000fd25",
          "Name": "yapilacakIslem",
          "SQLName": "yapilacakIslem",
          "IsActive": "CANCELLED"
        },
        {
          "ID": "8ba59417-b8fe-489f-8010-8b9093823c44",
          "Name": "api_adres",
          "SQLName": "api_adres",
          "IsActive": "http://localhost:7217/api"
        },
        {
          "ID": "91ffaf14-38da-40f9-b799-c3efcd4efef9",
          "Name": "ana_kaynak",
          "SQLName": "ana_kaynak",
          "IsActive": "CAD"
        },
        {
          "ID": "965ae372-cba3-41f1-b0f1-46728402d3fc",
          "Name": "alt_endpoint",
          "SQLName": "alt_endpoint",
          "IsActive": "CANCELLED_CAD"
        },
        {
          "ID": "6e67320a-353d-4447-9da0-da6a55434582",
          "Name": "CreatedOn",
          "SQLName": "CreatedOn",
          "IsActive": "true"
        },
        {
          "ID": "0907187b-3b83-4235-a279-9c67b66b8100",
          "Name": "ID",
          "SQLName": "ID",
          "IsActive": "true"
        },
        {
          "ID": "a8ad0422-dda7-4e6c-96ac-4985ca70992f",
          "Name": "LastModified",
          "SQLName": "LastModified",
          "IsActive": "true"
        },
        {
          "ID": "b5de405a-6ecf-41c1-8ddb-93cb17c04cfd",
          "Name": "AuthAppVersion",
          "SQLName": "AuthAppVersion",
          "IsActive": "true"
        },
        {
          "ID": "4a3920fe-a746-4d04-b8dc-2f46e8a60584",
          "Name": "AuthoringApplication",
          "SQLName": "AuthoringApplication",
          "IsActive": "true"
        },
        {
          "ID": "dbd3457b-c287-4e5c-844f-d7e6ff78f451",
          "Name": "CabinetName",
          "SQLName": "CabinetName",
          "IsActive": "true"
        },
        {
          "ID": "06574a03-47f1-40cc-b11c-e1dc20711185",
          "Name": "Category",
          "SQLName": "Category",
          "IsActive": "true"
        },
        {
          "ID": "8599a2c2-14b3-470c-adb9-f586f21c7ab2",
          "Name": "ChangeStatus",
          "SQLName": "ChangeStatus",
          "IsActive": "true"
        },
        {
          "ID": "97d0de77-d42f-401f-95bf-560bb41b4a0c",
          "Name": "CheckOutStatus",
          "SQLName": "CheckOutStatus",
          "IsActive": "true"
        },
        {
          "ID": "3fd77f94-c523-4087-ba20-a187a1d9ef80",
          "Name": "CheckoutState",
          "SQLName": "CheckoutState",
          "IsActive": "true"
        },
        {
          "ID": "1ccd4bee-e80e-436b-886f-a41d602ebbc7",
          "Name": "Comments",
          "SQLName": "Comments",
          "IsActive": "true"
        },
        {
          "ID": "a7435345-9306-41c7-9df2-7ece6fed6dcf",
          "Name": "ComponentType",
          "SQLName": "ComponentType",
          "IsActive": "true"
        },
        {
          "ID": "10f8e5b8-8253-4671-99cd-c315bfde63f2",
          "Name": "CreatedBy",
          "SQLName": "CreatedBy",
          "IsActive": "true"
        },
        {
          "ID": "b0a573d0-ad7e-4cd3-b6fd-803fac14f1e2",
          "Name": "DenemeNX",
          "SQLName": "DenemeNX",
          "IsActive": "true"
        },
        {
          "ID": "8817c693-bddf-4654-aa4b-2060ce3b7e42",
          "Name": "Derived",
          "SQLName": "Derived",
          "IsActive": "true"
        },
        {
          "ID": "63d4655e-229a-4755-a4c9-472ab1d4712a",
          "Name": "Description",
          "SQLName": "Description",
          "IsActive": "true"
        },
        {
          "ID": "aab46069-f2ed-4c1c-95ed-8ea67e10012c",
          "Name": "FamilyTableStatus",
          "SQLName": "FamilyTableStatus",
          "IsActive": "true"
        },
        {
          "ID": "26a2f8a2-e49e-4f43-bb9d-326986df28a8",
          "Name": "FileName",
          "SQLName": "FileName",
          "IsActive": "true"
        },
        {
          "ID": "083d761f-46e5-4c21-a8ab-d618b0599028",
          "Name": "FolderLocation",
          "SQLName": "FolderLocation",
          "IsActive": "true"
        },
        {
          "ID": "d48b9aef-8e41-4e70-8f4f-7160c17e5db3",
          "Name": "FolderName",
          "SQLName": "FolderName",
          "IsActive": "true"
        },
        {
          "ID": "8e90fe00-640f-4ef8-846f-7801435ac066",
          "Name": "GeneralStatus",
          "SQLName": "GeneralStatus",
          "IsActive": "true"
        },
        {
          "ID": "4bd05026-87af-4c7c-be14-84a4b9e5d91d",
          "Name": "Generic",
          "SQLName": "Generic",
          "IsActive": "true"
        },
        {
          "ID": "0f6f458f-fa36-4c8e-8e1c-8977e72644b8",
          "Name": "Identity",
          "SQLName": "Identity",
          "IsActive": "true"
        },
        {
          "ID": "9b6d755a-d243-4a01-b784-72e0d07e1846",
          "Name": "Instance",
          "SQLName": "Instance",
          "IsActive": "true"
        },
        {
          "ID": "b6e614d9-179f-43dc-bc10-dcaf5afecb05",
          "Name": "Kaleargenumber",
          "SQLName": "Kaleargenumber",
          "IsActive": "true"
        },
        {
          "ID": "70bfd37a-7388-46db-9933-6e529188245b",
          "Name": "Latest",
          "SQLName": "Latest",
          "IsActive": "true"
        },
        {
          "ID": "42d1b4c7-69ca-4d16-9099-4d97938f2f9c",
          "Name": "Length",
          "SQLName": "Length",
          "IsActive": "true"
        },
        {
          "ID": "470481e4-04fd-47f4-8f61-ae0faf46c644",
          "Name": "LifeCycleTemplateName",
          "SQLName": "LifeCycleTemplateName",
          "IsActive": "true"
        },
        {
          "ID": "84f0fc27-c452-4154-ac3c-0906129d4dde",
          "Name": "Mass",
          "SQLName": "Mass",
          "IsActive": "true"
        },
        {
          "ID": "4a68046a-5a1c-4d3f-ab13-83b345d6318b",
          "Name": "Mass1",
          "SQLName": "Mass1",
          "IsActive": "true"
        },
        {
          "ID": "05da7880-2e1a-4b92-9bae-6de96102c0bd",
          "Name": "Mass11",
          "SQLName": "Mass11",
          "IsActive": "true"
        },
        {
          "ID": "a21fceab-13f7-4eb1-821a-0b3ceb0cec69",
          "Name": "MassTest",
          "SQLName": "MassTest",
          "IsActive": "true"
        },
        {
          "ID": "78d9bda8-a95a-42f5-9d7e-1b1480c45243",
          "Name": "Material",
          "SQLName": "Material",
          "IsActive": "true"
        },
        {
          "ID": "554699e5-e743-4159-b9c3-c58c04ddecb3",
          "Name": "MissingDependents",
          "SQLName": "MissingDependents",
          "IsActive": "true"
        },
        {
          "ID": "7b98d12c-4b98-455c-bf8d-2bc7f9bcfaa0",
          "Name": "ModifiedBy",
          "SQLName": "ModifiedBy",
          "IsActive": "true"
        },
        {
          "ID": "c8bac0d0-7c50-4a04-a863-d95688082614",
          "Name": "NAME10",
          "SQLName": "NAME10",
          "IsActive": "true"
        },
        {
          "ID": "d36d1fa9-9fe8-41c1-ba1d-56abe2325c8b",
          "Name": "NAME30",
          "SQLName": "NAME30",
          "IsActive": "true"
        },
        {
          "ID": "5d62e204-c6ed-4bda-8da2-f118f0c8bdbd",
          "Name": "NDVersion",
          "SQLName": "NDVersion",
          "IsActive": "true"
        },
        {
          "ID": "76fa5c4f-4e3e-4db1-88f2-ce05a7733649",
          "Name": "Name",
          "SQLName": "Name",
          "IsActive": "true"
        },
        {
          "ID": "482ccf0f-0ef7-49f2-bc3f-34858cd76d03",
          "Name": "Number",
          "SQLName": "Number",
          "IsActive": "true"
        },
        {
          "ID": "cd729b0e-8b7b-4c5a-92bd-6da047b35828",
          "Name": "ObjectType",
          "SQLName": "ObjectType",
          "IsActive": "true"
        },
        {
          "ID": "45fccf4e-4549-43f7-918d-fe8ea5a2b28a",
          "Name": "OrganizationReference",
          "SQLName": "OrganizationReference",
          "IsActive": "true"
        },
        {
          "ID": "40794029-f894-4437-ab17-b4e9157162c3",
          "Name": "OwnerApplication",
          "SQLName": "OwnerApplication",
          "IsActive": "true"
        },
        {
          "ID": "2d1bfd06-8dfe-4a40-952c-ffaa32de9aef",
          "Name": "PARCAADI",
          "SQLName": "PARCAADI",
          "IsActive": "true"
        },
        {
          "ID": "aebe6afb-7d01-49ec-991c-91429be1c331",
          "Name": "Revision",
          "SQLName": "Revision",
          "IsActive": "true"
        },
        {
          "ID": "35b241b2-4ea7-4403-bb25-9eb3c46ad94b",
          "Name": "ShareStatus",
          "SQLName": "ShareStatus",
          "IsActive": "true"
        },
        {
          "ID": "58985e59-0f30-4326-adae-23431890e52b",
          "Name": "Source",
          "SQLName": "Source",
          "IsActive": "true"
        },
        {
          "ID": "030b554b-c6b8-49c7-b17f-344a556b3a5d",
          "Name": "Standard",
          "SQLName": "Standard",
          "IsActive": "true"
        },
        {
          "ID": "a9ca00e1-d3d6-47a8-b2e8-43000566a6c5",
          "Name": "Standard2",
          "SQLName": "Standard2",
          "IsActive": "true"
        },
        {
          "ID": "27e0cae6-f7de-4f5f-9398-dd5e39db5f1d",
          "Name": "State",
          "SQLName": "State",
          "IsActive": "true"
        },
        {
          "ID": "6b054a12-0c29-4ccd-b01a-7a8b58034efb",
          "Name": "SubCategory",
          "SQLName": "SubCategory",
          "IsActive": "true"
        },
        {
          "ID": "581f66ae-4892-422e-adc1-e54659e58301",
          "Name": "Supplier",
          "SQLName": "Supplier",
          "IsActive": "true"
        },
        {
          "ID": "d33529bd-80de-4d38-82a3-4c9c78b8e8ba",
          "Name": "Thickness",
          "SQLName": "Thickness",
          "IsActive": "true"
        },
        {
          "ID": "15657045-054a-4a24-829e-290d58ae55b1",
          "Name": "TypeDisplayName",
          "SQLName": "TypeDisplayName",
          "IsActive": "true"
        },
        {
          "ID": "bf97e294-3d4f-4f57-b8fd-a391f0441512",
          "Name": "TypeIcon",
          "SQLName": "TypeIcon",
          "IsActive": "true"
        },
        {
          "ID": "06a82b4e-cd88-4615-8aae-edb970f2f281",
          "Name": "Verified",
          "SQLName": "Verified",
          "IsActive": "true"
        },
        {
          "ID": "7aaa947e-1d02-4ae1-b167-e3fc87d24418",
          "Name": "Version",
          "SQLName": "Version",
          "IsActive": "true"
        },
        {
          "ID": "653e9237-2bf3-415b-b183-bb24f1610415",
          "Name": "VersionID",
          "SQLName": "VersionID",
          "IsActive": "true"
        },
        {
          "ID": "8d9bdda3-9631-47ef-bddc-666e83914f3b",
          "Name": "WorkInProgressState",
          "SQLName": "WorkInProgressState",
          "IsActive": "true"
        },
        {
          "ID": "ecd0753c-63e8-4bd7-8bcc-694f8ce06ad6",
          "Name": "@PTC.AppliedContainerContext.LocalTimeZone",
          "SQLName": "@PTC.AppliedContainerContext.LocalTimeZone",
          "IsActive": "true"
        }
      ]
    }
  ]
}